chrisdict/__init__.py
chrisdict/default.py
chrisdict/dictionary.py
chrisdict/mapping.py
chrisdict/merge.py
chrisdict/mixins.py
chrisdict-2.0.3.dist-info/LICENSE
chrisdict-2.0.3.dist-info/METADATA
chrisdict-2.0.3.dist-info/WHEEL
chrisdict-2.0.3.dist-info/top_level.txt
chrisdict-2.0.3.dist-info/zip-safe
chrisdict-2.0.3.dist-info/RECORD
