Metadata-Version: 2.1
Name: chrisdict
Version: 2.0.3
Summary: A dictionary that allows attribute-style access.
Home-page: https://github.com/chrisjihee/chrisdict
Author: Jihee Ryu
Author-email: chrisjihee@naver.com
License: MIT License
Classifier: Development Status :: 6 - Mature
Classifier: License :: OSI Approved :: MIT License
Classifier: Programming Language :: Python :: 3
Classifier: Programming Language :: Python :: 3.8
Classifier: Programming Language :: Python :: 3.9
Classifier: Programming Language :: Python :: 3.10
License-File: LICENSE
Requires-Dist: six
Provides-Extra: test
Requires-Dist: nose ; extra == 'test'
Requires-Dist: coverage ; extra == 'test'
